[
  {
    "word": "一期一会",
    "reading": "いちごいちえ",
    "meaning": "一生に一度の出会い"
  },
  {
    "word": "温故知新",
    "reading": "おんこちしん",
    "meaning": "古いことを学び、新しい知識を得る"
  },
  {
    "word": "七転八起",
    "reading": "しちてんはっき",
    "meaning": "何度失敗してもくじけず立ち上がること"
  },
  {
    "word": "千差万別",
    "reading": "せんさばんべつ",
    "meaning": "さまざまで違いが多いこと"
  },
  {
    "word": "十人十色",
    "reading": "じゅうにんといろ",
    "meaning": "人それぞれ考え方や好みが違うこと"
  },
  {
    "word": "四面楚歌",
    "reading": "しめんそか",
    "meaning": "周囲が敵や反対者ばかりで孤立すること"
  },
  {
    "word": "自画自賛",
    "reading": "じがじさん",
    "meaning": "自分で自分のことを褒めること"
  },
  {
    "word": "一石二鳥",
    "reading": "いっせきにちょう",
    "meaning": "一つの行動で二つの利益を得ること"
  },
  {
    "word": "試行錯誤",
    "reading": "しこうさくご",
    "meaning": "失敗を繰り返しながら解決方法を見つけること"
  },
  {
    "word": "以心伝心",
    "reading": "いしんでんしん",
    "meaning": "言葉を使わずに心が通じ合うこと"
  },
  {
    "word": "弱肉強食",
    "reading": "じゃくにくきょうしょく",
    "meaning": "弱いものが強いものに食われること"
  },
  {
    "word": "臥薪嘗胆",
    "reading": "がしんしょうたん",
    "meaning": "目的達成のために苦労を重ねること"
  },
  {
    "word": "起死回生",
    "reading": "きしかいせい",
    "meaning": "絶望的な状況から一気に立ち直ること"
  },
  {
    "word": "因果応報",
    "reading": "いんがおうほう",
    "meaning": "善悪の行いに応じた報いがあること"
  },
  {
    "word": "単刀直入",
    "reading": "たんとうちょくにゅう",
    "meaning": "前置きなく本題に入ること"
  },
  {
    "word": "電光石火",
    "reading": "でんこうせっか",
    "meaning": "動作が非常に素早いこと"
  },
  {
    "word": "二束三文",
    "reading": "にそくさんもん",
    "meaning": "非常に安い値段"
  },
  {
    "word": "三寒四温",
    "reading": "さんかんしおん",
    "meaning": "寒い日と暖かい日が交互に来ること"
  },
  {
    "word": "五里霧中",
    "reading": "ごりむちゅう",
    "meaning": "方向や見通しが立たないこと"
  },
  {
    "word": "晴耕雨読",
    "reading": "せいこううどく",
    "meaning": "晴れた日は畑を耕し雨の日は読書すること"
  },
  {
    "word": "不眠不休",
    "reading": "ふみんふきゅう",
    "meaning": "眠らず休まず働くこと"
  },
  {
    "word": "喜怒哀楽",
    "reading": "きどあいらく",
    "meaning": "人間のさまざまな感情"
  },
  {
    "word": "春夏秋冬",
    "reading": "しゅんかしゅうとう",
    "meaning": "四季のこと"
  },
  {
    "word": "東西南北",
    "reading": "とうざいなんぼく",
    "meaning": "四方のこと"
  },
  {
    "word": "右往左往",
    "reading": "うおうさおう",
    "meaning": "あわてて動き回ること"
  },
  {
    "word": "朝令暮改",
    "reading": "ちょうれいぼかい",
    "meaning": "命令や方針がすぐに変わること"
  },
  {
    "word": "悠々自適",
    "reading": "ゆうゆうじてき",
    "meaning": "のんびりと自由気ままに暮らすこと"
  },
  {
    "word": "一心不乱",
    "reading": "いっしんふらん",
    "meaning": "一つのことに集中すること"
  },
  {
    "word": "百発百中",
    "reading": "ひゃっぱつひゃくちゅう",
    "meaning": "すべて的中すること"
  },
  {
    "word": "猪突猛進",
    "reading": "ちょとつもうしん",
    "meaning": "向こう見ずに突き進むこと"
  },
  {
    "word": "針小棒大",
    "reading": "しんしょうぼうだい",
    "meaning": "小さなことを大げさに言うこと"
  },
  {
    "word": "前代未聞",
    "reading": "ぜんだいみもん",
    "meaning": "これまで聞いたことがないこと"
  },
  {
    "word": "油断大敵",
    "reading": "ゆだんたいてき",
    "meaning": "油断することは大きな失敗のもと"
  },
  {
    "word": "優柔不断",
    "reading": "ゆうじゅうふだん",
    "meaning": "決断力がないこと"
  },
  {
    "word": "無我夢中",
    "reading": "むがむちゅう",
    "meaning": "我を忘れて夢中になること"
  },
  {
    "word": "意気投合",
    "reading": "いきとうごう",
    "meaning": "気持ちがぴったり合うこと"
  },
  {
    "word": "質実剛健",
    "reading": "しつじつごうけん",
    "meaning": "飾り気がなく真面目で強いこと"
  },
  {
    "word": "創意工夫",
    "reading": "そういくふう",
    "meaning": "新しいアイデアを出して工夫すること"
  },
  {
    "word": "切磋琢磨",
    "reading": "せっさたくま",
    "meaning": "互いに励まし合い向上すること"
  },
  {
    "word": "一進一退",
    "reading": "いっしんいったい",
    "meaning": "進んだり退いたりすること"
  }
]
